bsnotifier/__init__.py
bsnotifier/__main__.py
bsnotifier/main.py
bsnotifier/version.py
bsnotifier/media/audio/alarm.wav
bsnotifier/media/images/low-battery.ico
bsnotifier-1.0.2.dist-info/LICENSE
bsnotifier-1.0.2.dist-info/METADATA
bsnotifier-1.0.2.dist-info/WHEEL
bsnotifier-1.0.2.dist-info/entry_points.txt
bsnotifier-1.0.2.dist-info/top_level.txt
bsnotifier-1.0.2.dist-info/RECORD
