Metadata-Version: 2.1
Name: bsnotifier
Version: 1.0.2
Summary: Command line application that shows a popup window when the battery is low
Home-page: https://github.com/eccanto/battery-status-notifier
Author: Erik Ccanto
Author-email: ccanto.erik@gmail.com
License: MIT
Keywords: battery,notifier,gui,popup
Classifier: Environment :: Console
Classifier: Operating System :: Unix
Classifier: Intended Audience :: Developers
Classifier: Operating System :: OS Independent
Classifier: Programming Language :: Python
Classifier: Programming Language :: Python :: 3
Classifier: License :: OSI Approved :: MIT License
Classifier: Development Status :: 4 - Beta
Classifier: Programming Language :: Python :: 3.7
Classifier: Programming Language :: Python :: 3.8
Classifier: Programming Language :: Python :: 3.9
Classifier: Programming Language :: Python :: 3.10
Classifier: Programming Language :: Python :: 3.11
Requires-Python: >=3.7.15, <4
License-File: LICENSE
Requires-Dist: pysimplegui (==4.60.4)
Requires-Dist: pillow (==9.3.0)
Requires-Dist: psutil (==5.9.4)
Requires-Dist: playsound (==1.3.0)
Requires-Dist: click (==8.1.3)
